cyclic_lamps/cyclic_lamp.v
module cyclic_lamp (clock,light);
	input clock;
	output reg [0:2] light;
	parameter s0=0,s1=1,s2=2;
	parameter red = 3'b100, yellow = 3'b010, green = 3'b001;
	reg [0:1] state;
	
	always@(posedge(clock))
		case(state)
		s0: state<=s1;
		s1: state<=s2;
		s2: state<=s0;
		default: state<=s0;
		endcase
	
	always@(state)
		case(state)
		s0: light=red;
		s1: light=yellow;
		s2: light=green;
		default: light=red;
		endcase
		
endmodule

cyclic_lamps/cyclic_lamp_tb.v
module cyclic_lamp_tb;
	reg clock;
	wire [0:2] light;
	
	cyclic_lamp LAMP (clock,light);
	always #5 clock=~clock;
	initial
		begin
		clock = 1'b0;
		#100 $finish;
		end
	initial
		begin
		$dumpfile("lamp.vcd");
		$dumpvars(0, cyclic_lamp_tb);
		$monitor($time, " : RYG1 : %b", light);
		end
endmodule

cyclic_lamps/lamp.vcd
$date
	Fri Jan 19 12:45:44 2024
$end
$version
	Icarus Verilog
$end
$timescale
	1s
$end
$scope module cyclic_lamp_tb $end
$var wire 3 ! light [0:2] $end
$var reg 1 " clock $end
$scope module LAMP $end
$var wire 1 " clock $end
$var parameter 3 # green $end
$var parameter 3 $ red $end
$var parameter 32 % s0 $end
$var parameter 32 & s1 $end
$var parameter 32 ' s2 $end
$var parameter 3 ( yellow $end
$var reg 3 ) light [0:2] $end
$var reg 2 * state [0:1] $end
$upscope $end
$upscope $end
$enddefinitions $end
$comment Show the parameter values. $end
$dumpall
b10 (
b10 '
b1 &
b0 %
b100 $
b1 #
$end
#0
$dumpvars
bx *
bx )
0"
bx !
$end
#5
b100 !
b100 )
b0 *
1"
#10
0"
#15
b10 !
b10 )
b1 *
1"
#20
0"
#25
b1 !
b1 )
b10 *
1"
#30
0"
#35
b100 !
b100 )
b0 *
1"
#40
0"
#45
b10 !
b10 )
b1 *
1"
#50
0"
#55
b1 !
b1 )
b10 *
1"
#60
0"
#65
b100 !
b100 )
b0 *
1"
#70
0"
#75
b10 !
b10 )
b1 *
1"
#80
0"
#85
b1 !
b1 )
b10 *
1"
#90
0"
#95
b100 !
b100 )
b0 *
1"
