parity detector/parity_gen.v
module parity_gen (x, clk, z);
	input x;
	input clk;
	output reg z;
	reg even_odd;
	parameter even=0, odd=1;
	
	always@(posedge(clk))
		case(even_odd)
		even : even_odd <= x ? odd : even;
		odd : even_odd <= x ? even : odd;
		default : even_odd <= even;
		endcase
		
	always@(even_odd)
		case(even_odd)
		even : z = 0;
		odd : z = 1;
		endcase
endmodule

parity detector/parity_gen_tb.v
module parity_gen_tb;
	reg x,clk;
	wire z;
	
	parity_gen PARY (x, clk, z);
	
	always
		#5 clk = ~clk;
		
	initial 
		begin
		clk = 1'b0;
		#100 $finish;
		end
	
	initial 
		begin
		#2 x=0; #10 x=1; #10 x=1; #10 x=0;
		#10 x=1; #10 x=1; #10 x=0; #10 x=1;
		#10 x=0; #10 x=0; #10 x=1;
		end
		
	initial begin
		$dumpfile("parity.vcd");
		$dumpvars(0,parity_gen_tb);
		$monitor($time, " x : %b, Z : %b",x,z);
		end
endmodule

parity detector/parity.vcd
$date
	Fri Jan 19 12:47:16 2024
$end
$version
	Icarus Verilog
$end
$timescale
	1s
$end
$scope module parity_gen_tb $end
$var wire 1 ! z $end
$var reg 1 " clk $end
$var reg 1 # x $end
$scope module PARY $end
$var wire 1 " clk $end
$var wire 1 # x $end
$var parameter 32 $ even $end
$var parameter 32 % odd $end
$var reg 1 & even_odd $end
$var reg 1 ! z $end
$upscope $end
$upscope $end
$enddefinitions $end
$comment Show the parameter values. $end
$dumpall
b1 %
b0 $
$end
#0
$dumpvars
x&
x#
0"
x!
$end
#2
0#
#5
0!
0&
1"
#10
0"
#12
1#
#15
1!
1&
1"
#20
0"
#25
0!
0&
1"
#30
0"
#32
0#
#35
1"
#40
0"
#42
1#
#45
1!
1&
1"
#50
0"
#55
0!
0&
1"
#60
0"
#62
0#
#65
1"
#70
0"
#72
1#
#75
1!
1&
1"
#80
0"
#82
0#
