PIPO Shift Register/pipo.v
`timescale 1ns/1ps
module pipo (o, clk, rst, i);
	input clk, rst;
	input [3:0] i;
	output [3:0] o;
	
	dff D1 (o[0],clk,rst,i[0]);
	dff D2 (o[1],clk,rst,i[1]);
	dff D3 (o[2],clk,rst,i[2]);
	dff D4 (o[3],clk,rst,i[3]);
	
endmodule

module dff (q,clk,rst,d);
	input clk, rst, d;
	output reg q;
	
	always@(posedge clk or rst)
	begin
	if (rst)
		q<=0;
	else
		q<= d;
	end
endmodule

PIPO Shift Register/pipo_tb.v
module pipo_tb;
	reg clk,rst;
	reg [3:0] i;
	wire [3:0] o;
	
	pipo DUT(o, clk, rst, i);
	
	always #5 clk = ~clk;
	
	initial 
	begin
		clk=0;rst=1;#5;
		rst=0;#5;
		i=0;#10;
		i=1;#10;
		i=2;#10;
		i=3;#10;
		i=4;#10;
		i=5;#10;
		i=6;#10;
		i=7;#10;
		i=8;#10;
		i=9;#10;
		i=10;#10;
		i=11;#10;
		i=12;#10;
		i=13;#10;
		i=14;#10;
		i=15;#10;
		#5 $finish;
	end
	
	initial
	begin
		$dumpfile("pipo.vcd");
		$dumpvars(0,pipo_tb);
		$monitor($time," rst:%b,i:%b,o:%b",rst,i,o);
	end
endmodule

PIPO Shift Register/pipo.vcd
$date
	Fri Jan 19 10:56:42 2024
$end
$version
	Icarus Verilog
$end
$timescale
	1ps
$end
$scope module pipo_tb $end
$var wire 4 ! o [3:0] $end
$var reg 1 " clk $end
$var reg 4 # i [3:0] $end
$var reg 1 $ rst $end
$scope module DUT $end
$var wire 1 " clk $end
$var wire 4 % i [3:0] $end
$var wire 1 $ rst $end
$var wire 4 & o [3:0] $end
$scope module D1 $end
$var wire 1 " clk $end
$var wire 1 ' d $end
$var wire 1 $ rst $end
$var reg 1 ( q $end
$upscope $end
$scope module D2 $end
$var wire 1 " clk $end
$var wire 1 ) d $end
$var wire 1 $ rst $end
$var reg 1 * q $end
$upscope $end
$scope module D3 $end
$var wire 1 " clk $end
$var wire 1 + d $end
$var wire 1 $ rst $end
$var reg 1 , q $end
$upscope $end
$scope module D4 $end
$var wire 1 " clk $end
$var wire 1 - d $end
$var wire 1 $ rst $end
$var reg 1 . q $end
$upscope $end
$upscope $end
$upscope $end
$enddefinitions $end
$comment Show the parameter values. $end
$dumpall
$end
#0
$dumpvars
0.
x-
0,
x+
0*
x)
0(
x'
b0 &
bx %
1$
bx #
0"
b0 !
$end
#5000
x.
x,
x*
bx !
bx &
x(
0$
1"
#10000
0'
0)
0+
0-
b0 #
b0 %
0"
#15000
0(
0*
0,
b0 !
b0 &
0.
1"
#20000
1'
0"
b1 #
b1 %
#25000
b1 !
b1 &
1(
1"
#30000
0'
1)
0"
b10 #
b10 %
#35000
0(
b10 !
b10 &
1*
1"
#40000
1'
0"
b11 #
b11 %
#45000
b11 !
b11 &
1(
1"
#50000
0'
0)
1+
0"
b100 #
b100 %
#55000
0(
0*
b100 !
b100 &
1,
1"
#60000
1'
0"
b101 #
b101 %
#65000
b101 !
b101 &
1(
1"
#70000
0'
1)
0"
b110 #
b110 %
#75000
0(
b110 !
b110 &
1*
1"
#80000
1'
0"
b111 #
b111 %
#85000
b111 !
b111 &
1(
1"
#90000
0'
0)
0+
1-
0"
b1000 #
b1000 %
#95000
0(
0*
0,
b1000 !
b1000 &
1.
1"
#100000
1'
0"
b1001 #
b1001 %
#105000
b1001 !
b1001 &
1(
1"
#110000
0'
1)
0"
b1010 #
b1010 %
#115000
0(
b1010 !
b1010 &
1*
1"
#120000
1'
0"
b1011 #
b1011 %
#125000
b1011 !
b1011 &
1(
1"
#130000
0'
0)
1+
0"
b1100 #
b1100 %
#135000
0(
0*
b1100 !
b1100 &
1,
1"
#140000
1'
0"
b1101 #
b1101 %
#145000
b1101 !
b1101 &
1(
1"
#150000
0'
1)
0"
b1110 #
b1110 %
#155000
0(
b1110 !
b1110 &
1*
1"
#160000
1'
0"
b1111 #
b1111 %
#165000
b1111 !
b1111 &
1(
1"
