fulladder/FA.v
module FA(a,b,cin,sum,cout);
  output sum, cout;
  input a, b,cin;
  always@(a,b,cin);
  assign sum = a^b^cin;
  assign cout = (a&b)|(b&cin)|(cin&a);
endmodule

fulladder/FA_tb.v
module FA_tb();
  
  reg  a,b,cin;
  wire  sum,cout;
  
  FA uut(a,b,cin,sum,cout);
  
  initial
    begin
      a =0; b =0;cin =0;
  #20; a =0; b =0;cin =1;
  #20; a =0; b =1;cin =0;
  #20; a =0; b =1;cin =1;
  #20; a =1; b =0;cin =0;
  #20; a =1; b =0;cin =1;
  #20; a =1; b =1;cin =0;
  #20; a =1; b =1;cin =1;
  #20;
    end
initial
    begin
      $dumpfile("full.vcd");
      $dumpvars(0,FA_tb);
      $monitor(a,b,cin);
    end
endmodule

fulladder/full.vcd
$date
	Fri Jan 19 10:13:39 2024
$end
$version
	Icarus Verilog
$end
$timescale
	1s
$end
$scope module FA_tb $end
$var wire 1 ! sum $end
$var wire 1 " cout $end
$var reg 1 # a $end
$var reg 1 $ b $end
$var reg 1 % cin $end
$scope module uut $end
$var wire 1 # a $end
$var wire 1 $ b $end
$var wire 1 % cin $end
$var wire 1 " cout $end
$var wire 1 ! sum $end
$upscope $end
$upscope $end
$enddefinitions $end
$comment Show the parameter values. $end
$dumpall
$end
#0
$dumpvars
0%
0$
0#
0"
0!
$end
#20
1!
1%
#40
0%
1$
#60
1"
0!
1%
#80
0"
1!
0%
0$
1#
#100
1"
0!
1%
#120
0%
1$
#140
1!
1%
