JK flip flop/jff.v
`timescale 1ns/1ps
module jff (q,q_bar,clk,rst,j,k);
	input clk, rst, j, k;
	output reg q, q_bar;
	
	always@(posedge clk or rst)
	begin
	if (rst)
		q<=0;
	else
		if (j==0 & k==0)
			q<=q;
		else if (j==0 & k==1)
			q<=0;
		else if (j==1 & k==0)
			q<=1;
		else if (j==1 & k==1)
			q<= ~q;
	end
	always #1 q_bar<=~q;
endmodule

JK flip flop/jff_tb.v
module jff_tb ;
	reg clk, rst, j, k;
	wire q,q_bar;
	
	jff DUT(q,q_bar,clk,rst,j,k);
	
	initial
	begin
		$dumpfile("jff.vcd");
		$dumpvars(0,jff_tb);
		$monitor($time," rst:%b,j:%b,k:%b,q:%b,q_bar:%b",rst,j,k,q,q_bar);
	end
	
	always #5 clk = ~clk;
	
	initial
	begin
	clk=0;j=0;k=0;#10;
	rst=1;j=0;k=1;#10;
	rst=1;j=1;k=0;#10;
	rst=0;j=1;k=1;#10;
	j=0;k=0;#10;
	j=0;k=1;#10;
	j=1;k=0;#10;
	j=1;k=1;#10;
	#20 $finish ;
	end
endmodule

JK flip flop/jff.vcd
$date
	Fri Jan 19 10:46:26 2024
$end
$version
	Icarus Verilog
$end
$timescale
	1ps
$end
$scope module jff_tb $end
$var wire 1 ! q_bar $end
$var wire 1 " q $end
$var reg 1 # clk $end
$var reg 1 $ j $end
$var reg 1 % k $end
$var reg 1 & rst $end
$scope module DUT $end
$var wire 1 # clk $end
$var wire 1 $ j $end
$var wire 1 % k $end
$var wire 1 & rst $end
$var reg 1 " q $end
$var reg 1 ! q_bar $end
$upscope $end
$upscope $end
$enddefinitions $end
$comment Show the parameter values. $end
$dumpall
$end
#0
$dumpvars
x&
0%
0$
0#
x"
x!
$end
#5000
1#
#10000
0"
0#
1%
1&
#11000
1!
#15000
1#
#20000
0#
0%
1$
#25000
1#
#30000
1"
0#
1%
0&
#31000
0!
#35000
0"
1#
#36000
1!
#40000
0#
0%
0$
#45000
1#
#50000
0#
1%
#55000
1#
#60000
0#
0%
1$
#65000
1"
1#
#66000
0!
#70000
0#
1%
#75000
0"
1#
#76000
1!
#80000
0#
#85000
1"
1#
#86000
0!
#90000
0#
#95000
0"
1#
#96000
1!
