PISO Shift Register/piso.v
`timescale 1ns/1ps
module piso (o, clk, rst, ld, i);
	input clk, rst, ld;
	input [3:0] i;
	output reg o;
	reg [3:0] a;
	
	always@(posedge clk | rst)
	begin
		if (rst)
			o<=0;
		else if (ld)
			a[3:0]<=i[3:0];
		else if (clk)
			a[3:1]<=a[2:0];
	end
	always #1 o<=a[3];
endmodule

PISO Shift Register/piso_tb.v
module piso_tb;
	reg clk,rst,ld;
	reg [3:0] i;
	wire o;
	
	piso DUT(o, clk, rst, ld, i);
	
	always #5 clk = ~clk;
	
	initial 
	begin
		clk=0;rst=1;#5;
		rst=0;ld=0;#5;
		ld=1;i=10;#10;
		ld=0;#50
		#5 $finish;
	end
	
	initial
	begin
		$dumpfile("piso.vcd");
		$dumpvars(0,piso_tb);
		$monitor($time," rst:%b,i:%b,o:%b",rst,i,o);
	end
endmodule

PISO Shift Register/piso.vcd
$date
	Fri Jan 19 11:00:30 2024
$end
$version
	Icarus Verilog
$end
$timescale
	1ps
$end
$scope module piso_tb $end
$var wire 1 ! o $end
$var reg 1 " clk $end
$var reg 4 # i [3:0] $end
$var reg 1 $ ld $end
$var reg 1 % rst $end
$scope module DUT $end
$var wire 1 " clk $end
$var wire 4 & i [3:0] $end
$var wire 1 $ ld $end
$var wire 1 % rst $end
$var reg 4 ' a [3:0] $end
$var reg 1 ! o $end
$upscope $end
$upscope $end
$enddefinitions $end
$comment Show the parameter values. $end
$dumpall
$end
#0
$dumpvars
bx '
bx &
1%
x$
bx #
0"
0!
$end
#1000
x!
#5000
0$
0%
1"
#10000
b1010 #
b1010 &
1$
0"
#15000
b1010 '
1"
#16000
1!
#20000
0"
0$
#25000
b100 '
1"
#26000
0!
#30000
0"
#35000
b1000 '
1"
#36000
1!
#40000
0"
#45000
b0 '
1"
#46000
0!
