SISO Shift Register/siso.v
`timescale 1ns/1ps
module siso (o, clk, rst, i);
	input clk, rst;
	input i;
	output o;
	wire [2:0] a;
	
	dff D1 (a[0],clk,rst,i);
	dff D2 (a[1],clk,rst,a[0]);
	dff D3 (a[2],clk,rst,a[1]);
	dff D4 (o,clk,rst,a[2]);
	
endmodule

module dff (q,clk,rst,d);
	input clk, rst, d;
	output reg q;
	
	always@(posedge clk or rst)
	begin
	if (rst)
		q<=0;
	else
		q<= d;
	end
endmodule

SISO Shift Register/siso_tb.v
module siso_tb;
	reg clk,rst;
	reg i;
	wire o;
	
	siso DUT(o, clk, rst, i);
	
	always #5 clk = ~clk;
	
	initial 
	begin
		clk=0;rst=1;#5;
		rst=0;#5;
		i=0;#40;
		i=1;#40;
		i=0;#40;
		i=1;#40;
		i=0;#40;
		i=1;#40;
		i=0;#40;
		i=1;#40;
		i=0;#40;
		i=1;#40;
		i=0;#40;
		i=1;#40;
		i=0;#40;
		i=1;#40;
		i=0;#40;
		i=1;#40;
		#5 $finish;
	end
	
	initial
	begin
		$dumpfile("siso.vcd");
		$dumpvars(0,siso_tb);
		$monitor($time," rst:%b,i:%b,o:%b",rst,i,o);
	end
endmodule

SISO Shift Register/siso.vcd
$date
	Fri Jan 19 11:06:49 2024
$end
$version
	Icarus Verilog
$end
$timescale
	1ps
$end
$scope module siso_tb $end
$var wire 1 ! o $end
$var reg 1 " clk $end
$var reg 1 # i $end
$var reg 1 $ rst $end
$scope module DUT $end
$var wire 1 " clk $end
$var wire 1 # i $end
$var wire 1 $ rst $end
$var wire 1 ! o $end
$var wire 3 % a [2:0] $end
$scope module D1 $end
$var wire 1 " clk $end
$var wire 1 # d $end
$var wire 1 $ rst $end
$var reg 1 & q $end
$upscope $end
$scope module D2 $end
$var wire 1 " clk $end
$var wire 1 ' d $end
$var wire 1 $ rst $end
$var reg 1 ( q $end
$upscope $end
$scope module D3 $end
$var wire 1 " clk $end
$var wire 1 ) d $end
$var wire 1 $ rst $end
$var reg 1 * q $end
$upscope $end
$scope module D4 $end
$var wire 1 " clk $end
$var wire 1 + d $end
$var wire 1 $ rst $end
$var reg 1 ! q $end
$upscope $end
$upscope $end
$upscope $end
$enddefinitions $end
$comment Show the parameter values. $end
$dumpall
$end
#0
$dumpvars
0+
0*
0)
0(
0'
0&
b0 %
1$
x#
0"
0!
$end
#5000
x'
b0x %
x&
0$
1"
#10000
0#
0"
#15000
0'
x)
0&
b0x0 %
x(
1"
#20000
0"
#25000
x+
0)
x*
bx00 %
0(
1"
#30000
0"
#35000
0+
b0 %
0*
x!
1"
#40000
0"
#45000
0!
1"
#50000
0"
1#
#55000
1'
b1 %
1&
1"
#60000
0"
#65000
1)
b11 %
1(
1"
#70000
0"
#75000
1+
b111 %
1*
1"
#80000
0"
#85000
1!
1"
#90000
0"
0#
#95000
0'
b110 %
0&
1"
#100000
0"
#105000
0)
b100 %
0(
1"
#110000
0"
#115000
0+
b0 %
0*
1"
#120000
0"
#125000
0!
1"
#130000
0"
1#
#135000
1'
b1 %
1&
1"
#140000
0"
#145000
1)
b11 %
1(
1"
#150000
0"
#155000
1+
b111 %
1*
1"
#160000
0"
#165000
1!
1"
#170000
0"
0#
#175000
0'
b110 %
0&
1"
#180000
0"
#185000
0)
b100 %
0(
1"
#190000
0"
#195000
0+
b0 %
0*
1"
#200000
0"
#205000
0!
1"
#210000
0"
1#
#215000
1'
b1 %
1&
1"
#220000
0"
#225000
1)
b11 %
1(
1"
#230000
0"
#235000
1+
b111 %
1*
1"
#240000
0"
#245000
1!
1"
#250000
0"
0#
#255000
0'
b110 %
0&
1"
#260000
0"
#265000
0)
b100 %
0(
1"
#270000
0"
#275000
0+
b0 %
0*
1"
#280000
0"
#285000
0!
1"
#290000
0"
1#
#295000
1'
b1 %
1&
1"
#300000
0"
#305000
1)
b11 %
1(
1"
#310000
0"
#315000
1+
b111 %
1*
1"
#320000
0"
#325000
1!
1"
#330000
0"
0#
#335000
0'
b110 %
0&
1"
#340000
0"
#345000
0)
b100 %
0(
1"
#350000
0"
#355000
0+
b0 %
0*
1"
#360000
0"
#365000
0!
1"
#370000
0"
1#
#375000
1'
b1 %
1&
1"
#380000
0"
#385000
1)
b11 %
1(
1"
#390000
0"
#395000
1+
b111 %
1*
1"
#400000
0"
#405000
1!
1"
#410000
0"
0#
#415000
0'
b110 %
0&
1"
#420000
0"
#425000
0)
b100 %
0(
1"
#430000
0"
#435000
0+
b0 %
0*
1"
#440000
0"
#445000
0!
1"
#450000
0"
1#
#455000
1'
b1 %
1&
1"
#460000
0"
#465000
1)
b11 %
1(
1"
#470000
0"
#475000
1+
b111 %
1*
1"
#480000
0"
#485000
1!
1"
#490000
0"
0#
#495000
0'
b110 %
0&
1"
#500000
0"
#505000
0)
b100 %
0(
1"
#510000
0"
#515000
0+
b0 %
0*
1"
#520000
0"
#525000
0!
1"
#530000
0"
1#
#535000
1'
b1 %
1&
1"
#540000
0"
#545000
1)
b11 %
1(
1"
#550000
0"
#555000
1+
b111 %
1*
1"
#560000
0"
#565000
1!
1"
#570000
0"
0#
#575000
0'
b110 %
0&
1"
#580000
0"
#585000
0)
b100 %
0(
1"
#590000
0"
#595000
0+
b0 %
0*
1"
#600000
0"
#605000
0!
1"
#610000
0"
1#
#615000
1'
b1 %
1&
1"
#620000
0"
#625000
1)
b11 %
1(
1"
#630000
0"
#635000
1+
b111 %
1*
1"
#640000
0"
#645000
1!
1"
