D-flipflop/dff.v
`timescale 1ns/1ps
module dff (q,q_bar,clk,rst,d);
	input clk, rst, d;
	output reg q,q_bar;
	
	always@(posedge clk or rst)
	begin
	if (rst)
		q<=0;
	else
		q<= d;
	end
	always #1 q_bar<= ~q;
endmodule

D-flipflop/dff_tb.v
module dff_tb ;
	reg clk, rst, d;
	wire q,q_bar;
	
	dff DUT(q,q_bar,clk,rst,d);
	
	initial
	begin
		$dumpfile("dff.vcd");
		$dumpvars(0,dff_tb);
		$monitor($time," rst:%b,d:%b,q:%b,q_bar:%b",rst,d,q,q_bar);
	end
	
	always #5 clk = ~clk;
	
	initial
	begin
	clk=0;d=0;#10;
	rst=1;d=1;#10;
	rst=1;d=0;#10;
	rst=0;d=1;#10;
	d=0;#10;
	d=1;#10;
	d=0;#10;
	d=1;#10;
	#20 $finish ;
	end
endmodule

D-flipflop/dff.vcd
$date
	Fri Jan 19 10:43:09 2024
$end
$version
	Icarus Verilog
$end
$timescale
	1ps
$end
$scope module dff_tb $end
$var wire 1 ! q_bar $end
$var wire 1 " q $end
$var reg 1 # clk $end
$var reg 1 $ d $end
$var reg 1 % rst $end
$scope module DUT $end
$var wire 1 # clk $end
$var wire 1 $ d $end
$var wire 1 % rst $end
$var reg 1 " q $end
$var reg 1 ! q_bar $end
$upscope $end
$upscope $end
$enddefinitions $end
$comment Show the parameter values. $end
$dumpall
$end
#0
$dumpvars
x%
0$
0#
x"
x!
$end
#5000
0"
1#
#6000
1!
#10000
0#
1$
1%
#15000
1#
#20000
0#
0$
#25000
1#
#30000
1"
0#
1$
0%
#31000
0!
#35000
1#
#40000
0#
0$
#45000
0"
1#
#46000
1!
#50000
0#
1$
#55000
1"
1#
#56000
0!
#60000
0#
0$
#65000
0"
1#
#66000
1!
#70000
0#
1$
#75000
1"
1#
#76000
0!
