multiplexer/mux.v
module mux(o,s,i);
	input [7:0] i;
	input [2:0] s;
	output o;
	wire s0,s1,s2,a1,a2,a3,a4,a5,a6,a7,a8;
		not N1(s0,s[0]);
		not N2(s1,s[1]);
		not N3(s2,s[2]);
		and A1(a1,s0,s1,s2,i[0]);
		and A2(a2,s[0],s1,s2,i[1]);
		and A3(a3,s0,s[1],s2,i[2]);
		and A4(a4,s[0],s[1],s2,i[3]);
		and A5(a5,s0,s1,s[2],i[4]);
		and A6(a6,s[0],s1,s[2],i[5]);
		and A7(a7,s0,s[1],s[2],i[6]);
		and A8(a8,s[0],s[1],s[2],i[7]);
		or O1(o,a1,a2,a3,a4,a5,a6,a7,a8);
endmodule

multiplexer/mux_tb.v
module mux_tb;
  reg [2:0]s;
  reg [7:0]i;
  wire o;
  

  mux DUT(o,s,i);
  initial
    begin
      $dumpfile("mux.vcd");
      $dumpvars(0,mux_tb);
      $monitor($time, "s[2]=%b,s[1]=%b,s[0]=%b,o=%b",s[2],s[1],s[0],o);
      i[0]=0;i[1]=1;i[2]=0;i[3]=1;i[4]=0;i[5]=1;i[6]=0;i[7]=1;
      s[2]=0;s[1]=0;s[0]=0;#10;
      s[2]=0;s[1]=0;s[0]=1;#10;
      s[2]=0;s[1]=1;s[0]=0;#10;
      s[2]=0;s[1]=1;s[0]=1;#10;
      s[2]=1;s[1]=0;s[0]=0;#10;
      s[2]=1;s[1]=0;s[0]=1;#10;
      s[2]=1;s[1]=1;s[0]=0;#10;
      s[2]=1;s[1]=1;s[0]=1;#10;
	$finish;
    end
endmodule

multiplexer/mux.vcd
$date
	Fri Jan 19 10:32:40 2024
$end
$version
	Icarus Verilog
$end
$timescale
	1s
$end
$scope module mux_tb $end
$var wire 1 ! o $end
$var reg 8 " i [7:0] $end
$var reg 3 # s [2:0] $end
$scope module DUT $end
$var wire 1 $ a1 $end
$var wire 1 % a2 $end
$var wire 1 & a3 $end
$var wire 1 ' a4 $end
$var wire 1 ( a5 $end
$var wire 1 ) a6 $end
$var wire 1 * a7 $end
$var wire 1 + a8 $end
$var wire 8 , i [7:0] $end
$var wire 1 ! o $end
$var wire 3 - s [2:0] $end
$var wire 1 . s0 $end
$var wire 1 / s1 $end
$var wire 1 0 s2 $end
$upscope $end
$upscope $end
$enddefinitions $end
$comment Show the parameter values. $end
$dumpall
$end
#0
$dumpvars
10
1/
1.
b0 -
b10101010 ,
0+
0*
0)
0(
0'
0&
0%
0$
b0 #
b10101010 "
0!
$end
#10
1!
0.
1%
b1 #
b1 -
#20
0!
1.
0%
0/
b10 #
b10 -
#30
1!
0.
1'
b11 #
b11 -
#40
0!
1.
1/
0'
00
b100 #
b100 -
#50
1!
0.
1)
b101 #
b101 -
#60
0!
1.
0)
0/
b110 #
b110 -
#70
1!
0.
1+
b111 #
b111 -
