encoder/encoder.v
module encoder (i0,i1,i2,i3,i4,i5,i6,i7,a,b,c);
	input i0,i1,i2,i3,i4,i5,i6,i7;
	output a,b,c;
	assign a = i1|i3|i5|i7;
	assign b = i2|i3|i6|i7;
	assign c = i4|i5|i6|i7;
endmodule

encoder/encoder_tb.v
module encoder_tb();
	reg i0,i1,i2,i3,i4,i5,i6,i7;
	wire a,b,c;
	
	encoder uut(i0,i1,i2,i3,i4,i5,i6,i7,a,b,c);
	
	initial
	begin
		i0=1;i1=0;i2=0;i3=0;i4=0;i5=0;i6=0;i7=0;#10;
		i0=0;i1=1;i2=0;i3=0;i4=0;i5=0;i6=0;i7=0;#10;
		i0=0;i1=0;i2=1;i3=0;i4=0;i5=0;i6=0;i7=0;#10;
		i0=0;i1=0;i2=0;i3=1;i4=0;i5=0;i6=0;i7=0;#10;
		i0=0;i1=0;i2=0;i3=0;i4=1;i5=0;i6=0;i7=0;#10;
		i0=0;i1=0;i2=0;i3=0;i4=0;i5=1;i6=0;i7=0;#10;
		i0=0;i1=0;i2=0;i3=0;i4=0;i5=0;i6=1;i7=0;#10;
		i0=0;i1=0;i2=0;i3=0;i4=0;i5=0;i6=0;i7=1;#10;
	end
	
	initial
	begin
		$dumpfile("encoder.vcd");
		$dumpvars(0,encoder_tb);
		$monitor("i0:%b,i1:%b,i2:%b,i3:%b,i4:%b,i5:%b,i6:%b,i7:%b,a:%b,b:%b,c:%b",i0,i1,i2,i3,i4,i5,i6,i7,a,b,c);
	end
endmodule

encoder/encoder.vcd
$date
	Fri Jan 19 10:21:58 2024
$end
$version
	Icarus Verilog
$end
$timescale
	1s
$end
$scope module encoder_tb $end
$var wire 1 ! c $end
$var wire 1 " b $end
$var wire 1 # a $end
$var reg 1 $ i0 $end
$var reg 1 % i1 $end
$var reg 1 & i2 $end
$var reg 1 ' i3 $end
$var reg 1 ( i4 $end
$var reg 1 ) i5 $end
$var reg 1 * i6 $end
$var reg 1 + i7 $end
$scope module uut $end
$var wire 1 # a $end
$var wire 1 " b $end
$var wire 1 ! c $end
$var wire 1 $ i0 $end
$var wire 1 % i1 $end
$var wire 1 & i2 $end
$var wire 1 ' i3 $end
$var wire 1 ( i4 $end
$var wire 1 ) i5 $end
$var wire 1 * i6 $end
$var wire 1 + i7 $end
$upscope $end
$upscope $end
$enddefinitions $end
$comment Show the parameter values. $end
$dumpall
$end
#0
$dumpvars
0+
0*
0)
0(
0'
0&
0%
1$
0#
0"
0!
$end
#10
1#
1%
0$
#20
1"
0#
1&
0%
#30
1#
1'
0&
#40
1!
0#
0"
1(
0'
#50
1#
1)
0(
#60
1"
0#
1*
0)
#70
1#
1+
0*
