Demultiplexer/DMUX.v
module DMUX (o,s,i);
	input i;
	input [2:0] s;
	output [7:0] o;
	
	and A1(o[0],~s[2],~s[1],~s[0],i);
	and A2(o[1],~s[2],~s[1],s[0],i);
	and A3(o[2],~s[2],s[1],~s[0],i);
	and A4(o[3],~s[2],s[1],s[0],i);
	and A5(o[4],s[2],~s[1],~s[0],i);
	and A6(o[5],s[2],~s[1],s[0],i);
	and A7(o[6],s[2],s[1],~s[0],i);
	and A8(o[7],s[2],s[1],s[0],i);
	
endmodule

Demultiplexer/DMUX_tb.v
module DMUX_tb ;
	reg i;
	reg [2:0] s;
	wire [7:0] o;
	
	DMUX DUT(o,s,i);
	initial 
		begin
			$dumpfile("DMUX.vcd");
			$dumpvars(0,DMUX_tb);
			$monitor("s[2]:%b,s[1]:%b,s[0]:%b,o:%b",s[2],s[1],s[0],o);
			i=1;
			s[2]=0;s[1]=0;s[0]=0;#10;
			s[2]=0;s[1]=0;s[0]=1;#10;
			s[2]=0;s[1]=1;s[0]=0;#10;
			s[2]=0;s[1]=1;s[0]=1;#10;
			s[2]=1;s[1]=0;s[0]=0;#10;
			s[2]=1;s[1]=0;s[0]=1;#10;
			s[2]=1;s[1]=1;s[0]=0;#10;
			s[2]=1;s[1]=1;s[0]=1;#10;
			$finish;
		end
endmodule

Demultiplexer/DMUX.vcd
$date
	Fri Jan 19 10:35:47 2024
$end
$version
	Icarus Verilog
$end
$timescale
	1s
$end
$scope module DMUX_tb $end
$var wire 8 ! o [7:0] $end
$var reg 1 " i $end
$var reg 3 # s [2:0] $end
$scope module DUT $end
$var wire 1 " i $end
$var wire 3 $ s [2:0] $end
$var wire 8 % o [7:0] $end
$upscope $end
$upscope $end
$enddefinitions $end
$comment Show the parameter values. $end
$dumpall
$end
#0
$dumpvars
b1 %
b0 $
b0 #
1"
b1 !
$end
#10
b10 !
b10 %
b1 #
b1 $
#20
b100 !
b100 %
b10 #
b10 $
#30
b1000 !
b1000 %
b11 #
b11 $
#40
b10000 !
b10000 %
b100 #
b100 $
#50
b100000 !
b100000 %
b101 #
b101 $
#60
b1000000 !
b1000000 %
b110 #
b110 $
#70
b10000000 !
b10000000 %
b111 #
b111 $
