series_detector/series.v
module series (clk, x, rst, z);
	input clk, x, rst;
	output reg z;
	reg [0:2] pstate, nstate;
	parameter s0=0, s1=1, s2=2, s3=3, s4=4, s5=5;
	
	always@(posedge clk or posedge rst)
		if (rst) pstate <= s0;
		else pstate <= nstate;
		
	always@(pstate,x)
		case(pstate)
		s0 : begin z = x ? 0:0; nstate <= x ? s1 : s0; end
		s1 : begin z = x ? 0:0; nstate <= x ? s1 : s2; end
		s2 : begin z = x ? 0:0; nstate <= x ? s3 : s0; end
		s3 : begin z = x ? 0:0; nstate <= x ? s0 : s4; end
		s4 : begin z = x ? 0:0; nstate <= x ? s5 : s0; end
		s5 : begin z = x ? 1:1; nstate <= x ? s4 : s0; end
		endcase
		
endmodule

series_detector/series_tb.v
module series_tb;
	reg clk, rst, x;
	wire z;
	
	series SER (clk, x, rst, z);
	
	always #5 clk = ~clk;
	
	initial 
		begin
		$dumpfile("series.vcd");
		$dumpvars(0,series_tb);
		$monitor($time, " rst : %b, x : %b, z : %b", rst, x, z);
		clk = 1'b0;
		end
		
	initial 
		begin
		#1 rst=0; x=0;
		#1 rst=1; x=0;
		#1 rst=0; x=0;
		#10 x=1; #10 x=1; #10 x=0; #10 x=1; #10 x=0; #10 x=1; #10 x=0; #10 x=1; #10 x=1; #10 $finish;
		end
endmodule

series_detector/series.vcd
$date
	Fri Jan 19 12:48:57 2024
$end
$version
	Icarus Verilog
$end
$timescale
	1s
$end
$scope module series_tb $end
$var wire 1 ! z $end
$var reg 1 " clk $end
$var reg 1 # rst $end
$var reg 1 $ x $end
$scope module SER $end
$var wire 1 " clk $end
$var wire 1 # rst $end
$var wire 1 $ x $end
$var parameter 32 % s0 $end
$var parameter 32 & s1 $end
$var parameter 32 ' s2 $end
$var parameter 32 ( s3 $end
$var parameter 32 ) s4 $end
$var parameter 32 * s5 $end
$var reg 3 + nstate [0:2] $end
$var reg 3 , pstate [0:2] $end
$var reg 1 ! z $end
$upscope $end
$upscope $end
$enddefinitions $end
$comment Show the parameter values. $end
$dumpall
b101 *
b100 )
b11 (
b10 '
b1 &
b0 %
$end
#0
$dumpvars
bx ,
bx +
x$
x#
0"
x!
$end
#1
0$
0#
#2
b0 +
0!
b0 ,
1#
#3
0#
#5
1"
#10
0"
#13
b1 +
1$
#15
b1 ,
1"
#20
0"
#25
1"
#30
0"
#33
b10 +
0$
#35
b0 +
b10 ,
1"
#40
0"
#43
b11 +
1$
#45
b0 +
b11 ,
1"
#50
0"
#53
b100 +
0$
#55
b0 +
b100 ,
1"
#60
0"
#63
b101 +
1$
#65
b100 +
1!
b101 ,
1"
#70
0"
#73
b0 +
0$
#75
0!
b0 ,
1"
#80
0"
#83
b1 +
1$
#85
b1 ,
1"
