Comparator/comp.v
module comp (o,a,b);
	input [1:0] a, b;
	output reg [1:0] o;
	// o=0 for a<b, o=1 for a>b, o=2 for a=b and for other condition o=3
	always@(a,b)
	begin
		if (a[1:0] < b[1:0]) 
		o=0;
		else if (a[1:0] > b[1:0]) 
		o=1;
		else if (a[1:0] == b[1:0]) 
		o=2;
		else
		o=3;
	end
endmodule

Comparator/comp_tb.v
module comp_tb;
	reg [1:0] a, b;
	wire [1:0] o;
	
	comp DUT(o,a,b);
	
	initial 
	begin
		a=0;b=0;#10;
		a=0;b=1;#10;
		a=0;b=2;#10;
		a=0;b=3;#10;
		a=1;b=0;#10;
		a=1;b=1;#10;
		a=1;b=2;#10;
		a=1;b=3;#10;
		a=2;b=0;#10;
		a=2;b=1;#10;
		a=2;b=2;#10;
		a=2;b=3;#10;
		a=3;b=0;#10;
		a=3;b=1;#10;
		a=3;b=2;#10;
		a=3;b=3;#10;
		$finish;
	end
	
	initial
	begin
		$dumpfile("comp.vcd");
		$dumpvars(0,comp_tb);
		$monitor("a:%d,b:%d,o:%b",a,b,o);
	end
endmodule

Comparator/comp.vcd
$date
	Fri Jan 19 10:38:56 2024
$end
$version
	Icarus Verilog
$end
$timescale
	1s
$end
$scope module comp_tb $end
$var wire 2 ! o [1:0] $end
$var reg 2 " a [1:0] $end
$var reg 2 # b [1:0] $end
$scope module DUT $end
$var wire 2 $ a [1:0] $end
$var wire 2 % b [1:0] $end
$var reg 2 & o [1:0] $end
$upscope $end
$upscope $end
$enddefinitions $end
$comment Show the parameter values. $end
$dumpall
$end
#0
$dumpvars
b10 &
b0 %
b0 $
b0 #
b0 "
b10 !
$end
#10
b0 !
b0 &
b1 #
b1 %
#20
b10 #
b10 %
#30
b11 #
b11 %
#40
b1 !
b1 &
b0 #
b0 %
b1 "
b1 $
#50
b10 !
b10 &
b1 #
b1 %
#60
b0 !
b0 &
b10 #
b10 %
#70
b11 #
b11 %
#80
b1 !
b1 &
b0 #
b0 %
b10 "
b10 $
#90
b1 #
b1 %
#100
b10 !
b10 &
b10 #
b10 %
#110
b0 !
b0 &
b11 #
b11 %
#120
b1 !
b1 &
b0 #
b0 %
b11 "
b11 $
#130
b1 #
b1 %
#140
b10 #
b10 %
#150
b10 !
b10 &
b11 #
b11 %
